megakino/__init__.py
megakino/src/__init__.py
megakino/src/common.py
megakino/src/menu.py
megakino/src/parser.py
megakino/src/search.py
megakino/src/actions/__init__.py
megakino/src/actions/download.py
megakino/src/actions/syncplay.py
megakino/src/actions/watch.py
megakino/src/extractors/__init__.py
megakino/src/extractors/megakino.py
megakino/src/extractors/voe.py
megakino-0.6.1.dist-info/METADATA
megakino-0.6.1.dist-info/WHEEL
megakino-0.6.1.dist-info/entry_points.txt
megakino-0.6.1.dist-info/licenses/LICENSE
megakino-0.6.1.dist-info/RECORD
