Metadata-Version: 2.4
Name: megakino
Version: 0.6.1
Summary: A Megakino Downloader!
Project-URL: Homepage, https://github.com/Tmaster055/Megakino-Downloader
Project-URL: Issues, https://github.com/Tmaster055/Megakino-Downloader/issues
Author: Tmaster055
License-File: LICENSE
Classifier: License :: OSI Approved :: MIT License
Classifier: Operating System :: OS Independent
Classifier: Programming Language :: Python :: 3
Requires-Python: >=3.8
Requires-Dist: bs4
Requires-Dist: fake-useragent
Requires-Dist: requests
Requires-Dist: windows-curses; platform_system == 'Windows'
Requires-Dist: yt-dlp
